pytest_aiomoto/__init__.py
pytest_aiomoto/aiomoto_batch.py
pytest_aiomoto/aiomoto_fixtures.py
pytest_aiomoto/aiomoto_lambda.py
pytest_aiomoto/aiomoto_s3.py
pytest_aiomoto/aiomoto_s3fs.py
pytest_aiomoto/aiomoto_services.py
pytest_aiomoto/aws_batch.py
pytest_aiomoto/aws_batch_models.py
pytest_aiomoto/aws_clients.py
pytest_aiomoto/aws_cognito.py
pytest_aiomoto/aws_credentials.py
pytest_aiomoto/aws_host.py
pytest_aiomoto/aws_lambda.py
pytest_aiomoto/aws_regions.py
pytest_aiomoto/aws_s3.py
pytest_aiomoto/moto_services.py
pytest_aiomoto/plugin.py
pytest_aiomoto/s3_event.json
pytest_aiomoto/s3_object.py
pytest_aiomoto/utils.py
pytest_aiomoto/version.py
pytest_aiomoto-0.7.1.dist-info/LICENSE
pytest_aiomoto-0.7.1.dist-info/METADATA
pytest_aiomoto-0.7.1.dist-info/WHEEL
pytest_aiomoto-0.7.1.dist-info/entry_points.txt
pytest_aiomoto-0.7.1.dist-info/RECORD
