Metadata-Version: 2.1
Name: pytest-aiomoto
Version: 0.7.1
Summary: pytest-aiomoto
Home-page: https://github.com/dazza-codes/pytest-aiomoto
License: Apache-2.0
Keywords: Development Status :: 3 - Alpha,Topic :: Software Development :: Testing,Framework :: Pytest,Intended Audience :: Developers,Operating System :: OS Independent,Programming Language :: Python,Programming Language :: Python :: 3,Programming Language :: Python :: 3.8,Programming Language :: Python :: 3.9,Programming Language :: Python :: 3.10,Programming Language :: Python :: 3.11,Programming Language :: Python :: 3 :: Only,License :: OSI Approved :: Apache Software License
Author: Darren Weber
Author-email: dazza-codes@github.com
Requires-Python: >=3.8,<4.0
Classifier: License :: OSI Approved :: Apache Software License
Classifier: Programming Language :: Python :: 3
Classifier: Programming Language :: Python :: 3.8
Classifier: Programming Language :: Python :: 3.9
Classifier: Programming Language :: Python :: 3.10
Classifier: Programming Language :: Python :: 3.11
Provides-Extra: docs
Requires-Dist: aiofiles (>=22.0,<23.0)
Requires-Dist: mkdocs (>=1.3,<2.0) ; extra == "docs"
Requires-Dist: mkdocs-material (>=8.0,<9.0) ; extra == "docs"
Requires-Dist: mkdocstrings[python] (>=0.19.0,<0.20.0) ; extra == "docs"
Requires-Dist: moto[all,server] (>=4.0,<5.0)
Requires-Dist: pytest (>=7.0,<8.0)
Requires-Dist: pytest-asyncio (>=0.21,<0.22)
Requires-Dist: requests (>=2.0,<3.0)
Requires-Dist: s3fs[awscli,boto3] (>=2023.0,<2024.0)
Project-URL: Repository, https://github.com/dazza-codes/pytest-aiomoto.git
